__init__.py
build/__init__.py
build/lib/__init__.py
build/lib/build/__init__.py
build/lib/build/lib/__init__.py
build/lib/build/lib/build/__init__.py
build/lib/build/lib/build/lib/__init__.py
build/lib/build/lib/build/lib/build/__init__.py
build/lib/build/lib/build/lib/build/lib/__init__.py
build/lib/build/lib/build/lib/build/lib/build/__init__.py
build/lib/build/lib/build/lib/build/lib/build/lib/__init__.py
build/lib/build/lib/build/lib/build/lib/build/lib/build/__init__.py
build/lib/build/lib/build/lib/build/lib/build/lib/build/lib/__init__.py
build/lib/build/lib/build/lib/build/lib/build/lib/build/lib/build/__init__.py
build/lib/build/lib/build/lib/build/lib/build/lib/build/lib/build/lib/__init__.py
build/lib/build/lib/build/lib/build/lib/build/lib/build/lib/build/lib/build/__init__.py
build/lib/build/lib/build/lib/build/lib/build/lib/build/lib/build/lib/build/lib/__init__.py
build/lib/build/lib/build/lib/build/lib/build/lib/build/lib/build/lib/build/lib/nbdev_cards/__init__.py
build/lib/build/lib/build/lib/build/lib/build/lib/build/lib/build/lib/build/lib/nbdev_cards/_modidx.py
build/lib/build/lib/build/lib/build/lib/build/lib/build/lib/build/lib/build/lib/nbdev_cards/card.py
build/lib/build/lib/build/lib/build/lib/build/lib/build/lib/build/lib/build/lib/nbdev_cards/core.py
build/lib/build/lib/build/lib/build/lib/build/lib/build/lib/build/lib/build/lib/nbdev_cards/deck.py
build/lib/build/lib/build/lib/build/lib/build/lib/build/lib/build/lib/nbdev_cards/__init__.py
build/lib/build/lib/build/lib/build/lib/build/lib/build/lib/build/lib/nbdev_cards/_modidx.py
build/lib/build/lib/build/lib/build/lib/build/lib/build/lib/build/lib/nbdev_cards/card.py
build/lib/build/lib/build/lib/build/lib/build/lib/build/lib/build/lib/nbdev_cards/core.py
build/lib/build/lib/build/lib/build/lib/build/lib/build/lib/build/lib/nbdev_cards/deck.py
build/lib/build/lib/build/lib/build/lib/build/lib/build/lib/nbdev_cards/__init__.py
nbdev_cards2022-0.1.7.dist-info/LICENSE
nbdev_cards2022-0.1.7.dist-info/METADATA
nbdev_cards2022-0.1.7.dist-info/WHEEL
nbdev_cards2022-0.1.7.dist-info/entry_points.txt
nbdev_cards2022-0.1.7.dist-info/top_level.txt
nbdev_cards2022-0.1.7.dist-info/RECORD
