Metadata-Version: 2.1
Name: nbdev-cards2022
Version: 0.1.7
Summary: A test project using nbdev
Home-page: https://github.com/hdocmsu/nbdev_cards/
Author: Hung P. Do, PhD
Author-email: hdocmsu@gmail.com
License: Apache Software License 2.0
Keywords: nbdev
Platform: UNKNOWN
Classifier: Development Status :: 3 - Alpha
Classifier: Intended Audience :: Developers
Classifier: Natural Language :: English
Classifier: Programming Language :: Python :: 3.7
Classifier: Programming Language :: Python :: 3.8
Classifier: Programming Language :: Python :: 3.9
Classifier: Programming Language :: Python :: 3.10
Classifier: License :: OSI Approved :: Apache Software License
Requires-Python: >=3.7
License-File: LICENSE
Provides-Extra: dev
